Veritas/__init__.py
Veritas/args.py
Veritas/downloader.py
Veritas/generator_utils.py
Veritas/model.py
Veritas/modelApi.py
Veritas/nlpBackend.py
Veritas/test.py
Veritas/tokenizer.py
Veritas/data/dict.en.txt
Veritas/data/dict.sparql.txt
Veritas/data/dicts/dict.en.txt
Veritas/data/dicts/dict.sparql.txt
Veritass-0.0.6.data/data/data/dict.en.txt
Veritass-0.0.6.data/data/data/dict.sparql.txt
Veritass-0.0.6.dist-info/LICENSE
Veritass-0.0.6.dist-info/METADATA
Veritass-0.0.6.dist-info/WHEEL
Veritass-0.0.6.dist-info/top_level.txt
Veritass-0.0.6.dist-info/RECORD
