Metadata-Version: 2.1
Name: Veritass
Version: 0.0.6
Summary: A python package for checking text for false statments via the Semantic Web
Home-page: https://github.com/Flajt/Veritas
Author: Flajt
Author-email: tjhannover@gmail.com
License: GNU General Public License v3.0
Keywords: FakeNews ML DeepLearning fairseq
Platform: UNKNOWN
Classifier: Development Status :: 3 - Alpha
Classifier: Intended Audience :: Developers
Classifier: Topic :: Software Development :: Libraries
Classifier: License :: OSI Approved :: GNU General Public License v3 (GPLv3)
Classifier: Programming Language :: Python :: 3.5
Classifier: Programming Language :: Python :: 3.6
Requires-Python: >3.5.0
Requires-Dist: torch (==1.5.1)
Requires-Dist: fairseq (==0.7.2)
Requires-Dist: spacy (>=2.3.2)
Requires-Dist: tqdm (>=4.49.0)
